m4/__init__.py
m4/api.py
m4/auth.py
m4/cli.py
m4/config.py
m4/console.py
m4/core/__init__.py
m4/core/backends/__init__.py
m4/core/backends/base.py
m4/core/backends/bigquery.py
m4/core/backends/duckdb.py
m4/core/datasets.py
m4/core/derived/__init__.py
m4/core/derived/builtins/__init__.py
m4/core/derived/builtins/mimic_iv/comorbidity/charlson.sql
m4/core/derived/builtins/mimic_iv/demographics/age.sql
m4/core/derived/builtins/mimic_iv/demographics/icustay_detail.sql
m4/core/derived/builtins/mimic_iv/demographics/icustay_hourly.sql
m4/core/derived/builtins/mimic_iv/demographics/icustay_times.sql
m4/core/derived/builtins/mimic_iv/demographics/weight_durations.sql
m4/core/derived/builtins/mimic_iv/duckdb.sql
m4/core/derived/builtins/mimic_iv/firstday/first_day_bg.sql
m4/core/derived/builtins/mimic_iv/firstday/first_day_bg_art.sql
m4/core/derived/builtins/mimic_iv/firstday/first_day_gcs.sql
m4/core/derived/builtins/mimic_iv/firstday/first_day_height.sql
m4/core/derived/builtins/mimic_iv/firstday/first_day_lab.sql
m4/core/derived/builtins/mimic_iv/firstday/first_day_rrt.sql
m4/core/derived/builtins/mimic_iv/firstday/first_day_sofa.sql
m4/core/derived/builtins/mimic_iv/firstday/first_day_urine_output.sql
m4/core/derived/builtins/mimic_iv/firstday/first_day_vitalsign.sql
m4/core/derived/builtins/mimic_iv/firstday/first_day_weight.sql
m4/core/derived/builtins/mimic_iv/measurement/bg.sql
m4/core/derived/builtins/mimic_iv/measurement/blood_differential.sql
m4/core/derived/builtins/mimic_iv/measurement/cardiac_marker.sql
m4/core/derived/builtins/mimic_iv/measurement/chemistry.sql
m4/core/derived/builtins/mimic_iv/measurement/coagulation.sql
m4/core/derived/builtins/mimic_iv/measurement/complete_blood_count.sql
m4/core/derived/builtins/mimic_iv/measurement/creatinine_baseline.sql
m4/core/derived/builtins/mimic_iv/measurement/enzyme.sql
m4/core/derived/builtins/mimic_iv/measurement/gcs.sql
m4/core/derived/builtins/mimic_iv/measurement/height.sql
m4_infra-0.4.2.dist-info/METADATA
m4_infra-0.4.2.dist-info/WHEEL
m4_infra-0.4.2.dist-info/entry_points.txt
m4_infra-0.4.2.dist-info/licenses/LICENSE
m4_infra-0.4.2.dist-info/RECORD
