Metadata-Version: 2.4
Name: m4-infra
Version: 0.4.2
Summary: Infrastructure for AI-assisted clinical research with EHR datasets
Keywords: mimic-iv,clinical-data,mcp,llm,medical,healthcare,duckdb,bigquery
Author-Email: Rafi Al Attrach <rafiaa@mit.edu>, Pedro Moreira <pedrojfm@mit.edu>, Rajna Fani <rajnaf@mit.edu>
Maintainer-Email: Rafi Al Attrach <rafiaa@mit.edu>, Pedro Moreira <pedrojfm@mit.edu>, Rajna Fani <rajnaf@mit.edu>
License-Expression: MIT
Classifier: Development Status :: 4 - Beta
Classifier: Intended Audience :: Science/Research
Classifier: Intended Audience :: Healthcare Industry
Classifier: Topic :: Scientific/Engineering :: Medical Science Apps.
Classifier: Topic :: Database :: Database Engines/Servers
Classifier: Programming Language :: Python :: 3
Classifier: Programming Language :: Python :: 3.10
Classifier: Programming Language :: Python :: 3.11
Classifier: Programming Language :: Python :: 3.12
Classifier: Operating System :: OS Independent
Project-URL: Homepage, https://github.com/rafiattrach/m4
Project-URL: Repository, https://github.com/rafiattrach/m4
Project-URL: Documentation, https://github.com/rafiattrach/m4#readme
Project-URL: Issues, https://github.com/rafiattrach/m4/issues
Project-URL: Changelog, https://github.com/rafiattrach/m4/releases
Requires-Python: >=3.10
Requires-Dist: typer>=0.9.0
Requires-Dist: rich>=13.0.0
Requires-Dist: requests>=2.30.0
Requires-Dist: beautifulsoup4>=4.12.0
Requires-Dist: pandas>=2.0.0
Requires-Dist: fastmcp>=0.1.0
Requires-Dist: google-cloud-bigquery>=3.0.0
Requires-Dist: pyarrow>=10.0.0
Requires-Dist: db-dtypes>=1.0.0
Requires-Dist: sqlparse>=0.4.0
Requires-Dist: pyjwt[crypto]>=2.8.0
Requires-Dist: cryptography>=41.0.0
Requires-Dist: python-jose[cryptography]>=3.3.0
Requires-Dist: httpx>=0.24.0
Requires-Dist: duckdb>=1.4.1
